{"name":"Search for a automation course","id":"academy-choucair;search-for-a-automation-course","testSteps":[{"number":1,"description":"Given than Camilo wants to learn automation at the academy Choucair\r\n| strUser | strPassword |\r\n| 1085292335 | Choucair2021* |","duration":15079,"startTime":"2021-03-16T21:25:37.858080-05:00[America/Bogota]","screenshots":[{"screenshot":"3ea01e0f45ad543f6a12a6acdc333b7a29b102e2116e5768e0b139cbd88c1dc3.png","timeStamp":1615947952937}],"result":"SUCCESS","precondition":false,"level":0,"lineNumber":0,"children":[{"number":2,"description":"Camilo open up","duration":7667,"startTime":"2021-03-16T21:25:38.733018600-05:00[America/Bogota]","screenshots":[{"screenshot":"d097bf954e6368d7309e913c521b6c9bbd717eaa1e8ecfef32a7dc5f5b7b0a49.png","timeStamp":1615947946400}],"result":"SUCCESS","precondition":false,"level":1,"lineNumber":0,"children":[{"number":3,"description":"Camilo opens the Choucair academy page","duration":7635,"startTime":"2021-03-16T21:25:38.748641900-05:00[America/Bogota]","screenshots":[{"screenshot":"d097bf954e6368d7309e913c521b6c9bbd717eaa1e8ecfef32a7dc5f5b7b0a49.png","timeStamp":1615947946384}],"result":"SUCCESS","precondition":false,"level":2,"lineNumber":0}]},{"number":4,"description":"Camilo login","duration":6495,"startTime":"2021-03-16T21:25:46.415719400-05:00[America/Bogota]","screenshots":[{"screenshot":"3ea01e0f45ad543f6a12a6acdc333b7a29b102e2116e5768e0b139cbd88c1dc3.png","timeStamp":1615947952911}],"result":"SUCCESS","precondition":false,"level":1,"lineNumber":0,"children":[{"number":5,"description":"Camilo clicks on button that shows us the form to login","duration":840,"startTime":"2021-03-16T21:25:46.462591500-05:00[America/Bogota]","screenshots":[{"screenshot":"194fea7ca46afa1cc2ac39241969319c0d7e81106c1c4b029f8757944f9f7bb0.png","timeStamp":1615947947303}],"result":"SUCCESS","precondition":false,"level":2,"lineNumber":0},{"number":6,"description":"Camilo enters \u00271085292335\u0027 into where do we write the user","duration":992,"startTime":"2021-03-16T21:25:47.303097900-05:00[America/Bogota]","screenshots":[{"screenshot":"c2f42e7b1cb9bf2a4d04887e5506d3fd65470f142f40d6246cebd1ce2c93df11.png","timeStamp":1615947948295}],"result":"SUCCESS","precondition":false,"level":2,"lineNumber":0},{"number":7,"description":"Camilo enters \u0027Choucair2021*\u0027 into where do we write the password","duration":956,"startTime":"2021-03-16T21:25:48.297966-05:00[America/Bogota]","screenshots":[{"screenshot":"bc364e3ef73e01cdaf369a600c58805989c83510b05a7759e47c57d74bc63018.png","timeStamp":1615947949254}],"result":"SUCCESS","precondition":false,"level":2,"lineNumber":0},{"number":8,"description":"Camilo clicks on button to confirm login","duration":3633,"startTime":"2021-03-16T21:25:49.256534-05:00[America/Bogota]","screenshots":[{"screenshot":"3ea01e0f45ad543f6a12a6acdc333b7a29b102e2116e5768e0b139cbd88c1dc3.png","timeStamp":1615947952890}],"result":"SUCCESS","precondition":false,"level":2,"lineNumber":0}]}]},{"number":9,"description":"When he search for the course on the choucair academy platform\r\n| strCourse |\r\n| Metodologia Bancolombia |","duration":11880,"startTime":"2021-03-16T21:25:52.939256-05:00[America/Bogota]","exception":{"errorType":"net.thucydides.core.webdriver.exceptions.ElementShouldBeEnabledException","message":"Expected enabled element was not enabled","stackTrace":[{"classLoaderName":"app","declaringClass":"co.com.choucair.certification.proyectobase1.tasks.Search","methodName":"performAs","fileName":"Search.java","lineNumber":24,"format":1},{"classLoaderName":"app","declaringClass":"co.com.choucair.certification.proyectobase1.stepdefinitions.ChoucairAcademyStepDefinitions","methodName":"heSearchForTheCourseRecursosAutomatizacionBancolombiaOnTheChoucairAcademyPlatform","fileName":"ChoucairAcademyStepDefinitions.java","lineNumber":32,"format":1},{"classLoaderName":"app","declaringClass":"cucumber.runner.Runner","methodName":"runPickle","fileName":"Runner.java","lineNumber":80,"format":1}],"rootCause":{"errorType":"org.openqa.selenium.TimeoutException","message":"Expected condition failed: waiting for By.id: coursesearchbox to be enabled (tried for 5 second(s) with 100 milliseconds interval)","stackTrace":[{"classLoaderName":"app","declaringClass":"co.com.choucair.certification.proyectobase1.tasks.Search","methodName":"performAs","fileName":"Search.java","lineNumber":24,"format":1},{"classLoaderName":"app","declaringClass":"co.com.choucair.certification.proyectobase1.stepdefinitions.ChoucairAcademyStepDefinitions","methodName":"heSearchForTheCourseRecursosAutomatizacionBancolombiaOnTheChoucairAcademyPlatform","fileName":"ChoucairAcademyStepDefinitions.java","lineNumber":32,"format":1},{"classLoaderName":"app","declaringClass":"cucumber.runner.Runner","methodName":"runPickle","fileName":"Runner.java","lineNumber":80,"format":1}],"rootCause":{"errorType":"org.openqa.selenium.NoSuchElementException","message":"no such element: Unable to locate element: {\"method\":\"css selector\",\"selector\":\"#coursesearchbox\"}\n  (Session info: chrome\u003d89.0.4389.90)\nFor documentation on this error, please visit: https://www.seleniumhq.org/exceptions/no_such_element.html\nBuild info: version: \u00273.141.59\u0027, revision: \u0027e82be7d358\u0027, time: \u00272018-11-14T08:17:03\u0027\nSystem info: host: \u0027DESKTOP-NKG37V4\u0027, ip: \u0027192.168.1.7\u0027, os.name: \u0027Windows 10\u0027, os.arch: \u0027amd64\u0027, os.version: \u002710.0\u0027, java.version: \u002711.0.4\u0027\nDriver info: org.openqa.selenium.chrome.ChromeDriver\nCapabilities {acceptInsecureCerts: false, browserName: chrome, browserVersion: 89.0.4389.90, chrome: {chromedriverVersion: 89.0.4389.23 (61b08ee2c5002..., userDataDir: C:\\Users\\ramze\\AppData\\Loca...}, goog:chromeOptions: {debuggerAddress: localhost:49790}, javascriptEnabled: true, networkConnectionEnabled: false, pageLoadStrategy: normal, platform: WINDOWS, platformName: WINDOWS, proxy: Proxy(), setWindowRect: true, strictFileInteractability: false, timeouts: {implicit: 0, pageLoad: 300000, script: 30000}, unhandledPromptBehavior: dismiss and notify, webauthn:extension:largeBlob: true, webauthn:virtualAuthenticators: true}\nSession ID: 78c3fdeff0595efeedae98873b18b425\n*** Element info: {Using\u003did, value\u003dcoursesearchbox}","stackTrace":[{"classLoaderName":"app","declaringClass":"co.com.choucair.certification.proyectobase1.tasks.Search","methodName":"performAs","fileName":"Search.java","lineNumber":24,"format":1},{"classLoaderName":"app","declaringClass":"co.com.choucair.certification.proyectobase1.stepdefinitions.ChoucairAcademyStepDefinitions","methodName":"heSearchForTheCourseRecursosAutomatizacionBancolombiaOnTheChoucairAcademyPlatform","fileName":"ChoucairAcademyStepDefinitions.java","lineNumber":32,"format":1},{"classLoaderName":"app","declaringClass":"cucumber.runner.Runner","methodName":"runPickle","fileName":"Runner.java","lineNumber":80,"format":1}]}}},"result":"FAILURE","precondition":false,"level":0,"lineNumber":0,"children":[{"number":10,"description":"Camilo search","duration":11859,"startTime":"2021-03-16T21:25:52.944282100-05:00[America/Bogota]","exception":{"errorType":"net.thucydides.core.webdriver.exceptions.ElementShouldBeEnabledException","message":"Expected enabled element was not enabled","stackTrace":[{"classLoaderName":"app","declaringClass":"co.com.choucair.certification.proyectobase1.tasks.Search","methodName":"performAs","fileName":"Search.java","lineNumber":24,"format":1},{"classLoaderName":"app","declaringClass":"co.com.choucair.certification.proyectobase1.stepdefinitions.ChoucairAcademyStepDefinitions","methodName":"heSearchForTheCourseRecursosAutomatizacionBancolombiaOnTheChoucairAcademyPlatform","fileName":"ChoucairAcademyStepDefinitions.java","lineNumber":32,"format":1},{"classLoaderName":"app","declaringClass":"cucumber.runner.Runner","methodName":"runPickle","fileName":"Runner.java","lineNumber":80,"format":1}],"rootCause":{"errorType":"org.openqa.selenium.TimeoutException","message":"Expected condition failed: waiting for By.id: coursesearchbox to be enabled (tried for 5 second(s) with 100 milliseconds interval)","stackTrace":[{"classLoaderName":"app","declaringClass":"co.com.choucair.certification.proyectobase1.tasks.Search","methodName":"performAs","fileName":"Search.java","lineNumber":24,"format":1},{"classLoaderName":"app","declaringClass":"co.com.choucair.certification.proyectobase1.stepdefinitions.ChoucairAcademyStepDefinitions","methodName":"heSearchForTheCourseRecursosAutomatizacionBancolombiaOnTheChoucairAcademyPlatform","fileName":"ChoucairAcademyStepDefinitions.java","lineNumber":32,"format":1},{"classLoaderName":"app","declaringClass":"cucumber.runner.Runner","methodName":"runPickle","fileName":"Runner.java","lineNumber":80,"format":1}],"rootCause":{"errorType":"org.openqa.selenium.NoSuchElementException","message":"no such element: Unable to locate element: {\"method\":\"css selector\",\"selector\":\"#coursesearchbox\"}\n  (Session info: chrome\u003d89.0.4389.90)\nFor documentation on this error, please visit: https://www.seleniumhq.org/exceptions/no_such_element.html\nBuild info: version: \u00273.141.59\u0027, revision: \u0027e82be7d358\u0027, time: \u00272018-11-14T08:17:03\u0027\nSystem info: host: \u0027DESKTOP-NKG37V4\u0027, ip: \u0027192.168.1.7\u0027, os.name: \u0027Windows 10\u0027, os.arch: \u0027amd64\u0027, os.version: \u002710.0\u0027, java.version: \u002711.0.4\u0027\nDriver info: org.openqa.selenium.chrome.ChromeDriver\nCapabilities {acceptInsecureCerts: false, browserName: chrome, browserVersion: 89.0.4389.90, chrome: {chromedriverVersion: 89.0.4389.23 (61b08ee2c5002..., userDataDir: C:\\Users\\ramze\\AppData\\Loca...}, goog:chromeOptions: {debuggerAddress: localhost:49790}, javascriptEnabled: true, networkConnectionEnabled: false, pageLoadStrategy: normal, platform: WINDOWS, platformName: WINDOWS, proxy: Proxy(), setWindowRect: true, strictFileInteractability: false, timeouts: {implicit: 0, pageLoad: 300000, script: 30000}, unhandledPromptBehavior: dismiss and notify, webauthn:extension:largeBlob: true, webauthn:virtualAuthenticators: true}\nSession ID: 78c3fdeff0595efeedae98873b18b425\n*** Element info: {Using\u003did, value\u003dcoursesearchbox}","stackTrace":[{"classLoaderName":"app","declaringClass":"co.com.choucair.certification.proyectobase1.tasks.Search","methodName":"performAs","fileName":"Search.java","lineNumber":24,"format":1},{"classLoaderName":"app","declaringClass":"co.com.choucair.certification.proyectobase1.stepdefinitions.ChoucairAcademyStepDefinitions","methodName":"heSearchForTheCourseRecursosAutomatizacionBancolombiaOnTheChoucairAcademyPlatform","fileName":"ChoucairAcademyStepDefinitions.java","lineNumber":32,"format":1},{"classLoaderName":"app","declaringClass":"cucumber.runner.Runner","methodName":"runPickle","fileName":"Runner.java","lineNumber":80,"format":1}]}}},"result":"FAILURE","precondition":false,"level":1,"lineNumber":0,"children":[{"number":11,"description":"Camilo clicks on Selecciona la universidad choucair","duration":1317,"startTime":"2021-03-16T21:25:52.991155500-05:00[America/Bogota]","screenshots":[{"screenshot":"f560f1ba6516231349a36ecf291aaa13650ade76e6760c1a06dc0cc15293bc31.png","timeStamp":1615947954308}],"result":"SUCCESS","precondition":false,"level":2,"lineNumber":0},{"number":12,"description":"Camilo enters \u0027Metodologia Bancolombia\u0027 into Buscar el curso","duration":10478,"startTime":"2021-03-16T21:25:54.310354800-05:00[America/Bogota]","screenshots":[{"screenshot":"f560f1ba6516231349a36ecf291aaa13650ade76e6760c1a06dc0cc15293bc31.png","htmlSource":"pagesource9398112199697390947.html.txt","timeStamp":1615947964772}],"exception":{"errorType":"net.thucydides.core.webdriver.exceptions.ElementShouldBeEnabledException","message":"Expected enabled element was not enabled","stackTrace":[{"classLoaderName":"app","declaringClass":"co.com.choucair.certification.proyectobase1.tasks.Search","methodName":"performAs","fileName":"Search.java","lineNumber":24,"format":1},{"classLoaderName":"app","declaringClass":"co.com.choucair.certification.proyectobase1.stepdefinitions.ChoucairAcademyStepDefinitions","methodName":"heSearchForTheCourseRecursosAutomatizacionBancolombiaOnTheChoucairAcademyPlatform","fileName":"ChoucairAcademyStepDefinitions.java","lineNumber":32,"format":1},{"classLoaderName":"app","declaringClass":"cucumber.runner.Runner","methodName":"runPickle","fileName":"Runner.java","lineNumber":80,"format":1}],"rootCause":{"errorType":"org.openqa.selenium.TimeoutException","message":"Expected condition failed: waiting for By.id: coursesearchbox to be enabled (tried for 5 second(s) with 100 milliseconds interval)","stackTrace":[{"classLoaderName":"app","declaringClass":"co.com.choucair.certification.proyectobase1.tasks.Search","methodName":"performAs","fileName":"Search.java","lineNumber":24,"format":1},{"classLoaderName":"app","declaringClass":"co.com.choucair.certification.proyectobase1.stepdefinitions.ChoucairAcademyStepDefinitions","methodName":"heSearchForTheCourseRecursosAutomatizacionBancolombiaOnTheChoucairAcademyPlatform","fileName":"ChoucairAcademyStepDefinitions.java","lineNumber":32,"format":1},{"classLoaderName":"app","declaringClass":"cucumber.runner.Runner","methodName":"runPickle","fileName":"Runner.java","lineNumber":80,"format":1}],"rootCause":{"errorType":"org.openqa.selenium.NoSuchElementException","message":"no such element: Unable to locate element: {\"method\":\"css selector\",\"selector\":\"#coursesearchbox\"}\n  (Session info: chrome\u003d89.0.4389.90)\nFor documentation on this error, please visit: https://www.seleniumhq.org/exceptions/no_such_element.html\nBuild info: version: \u00273.141.59\u0027, revision: \u0027e82be7d358\u0027, time: \u00272018-11-14T08:17:03\u0027\nSystem info: host: \u0027DESKTOP-NKG37V4\u0027, ip: \u0027192.168.1.7\u0027, os.name: \u0027Windows 10\u0027, os.arch: \u0027amd64\u0027, os.version: \u002710.0\u0027, java.version: \u002711.0.4\u0027\nDriver info: org.openqa.selenium.chrome.ChromeDriver\nCapabilities {acceptInsecureCerts: false, browserName: chrome, browserVersion: 89.0.4389.90, chrome: {chromedriverVersion: 89.0.4389.23 (61b08ee2c5002..., userDataDir: C:\\Users\\ramze\\AppData\\Loca...}, goog:chromeOptions: {debuggerAddress: localhost:49790}, javascriptEnabled: true, networkConnectionEnabled: false, pageLoadStrategy: normal, platform: WINDOWS, platformName: WINDOWS, proxy: Proxy(), setWindowRect: true, strictFileInteractability: false, timeouts: {implicit: 0, pageLoad: 300000, script: 30000}, unhandledPromptBehavior: dismiss and notify, webauthn:extension:largeBlob: true, webauthn:virtualAuthenticators: true}\nSession ID: 78c3fdeff0595efeedae98873b18b425\n*** Element info: {Using\u003did, value\u003dcoursesearchbox}","stackTrace":[{"classLoaderName":"app","declaringClass":"co.com.choucair.certification.proyectobase1.tasks.Search","methodName":"performAs","fileName":"Search.java","lineNumber":24,"format":1},{"classLoaderName":"app","declaringClass":"co.com.choucair.certification.proyectobase1.stepdefinitions.ChoucairAcademyStepDefinitions","methodName":"heSearchForTheCourseRecursosAutomatizacionBancolombiaOnTheChoucairAcademyPlatform","fileName":"ChoucairAcademyStepDefinitions.java","lineNumber":32,"format":1},{"classLoaderName":"app","declaringClass":"cucumber.runner.Runner","methodName":"runPickle","fileName":"Runner.java","lineNumber":80,"format":1}]}}},"result":"FAILURE","precondition":false,"level":2,"lineNumber":0}]}]},{"number":13,"description":"Then he finds the course called\r\n| strCourse |\r\n| Metodologia Bancolombia |","duration":0,"startTime":"2021-03-16T21:26:04.850957200-05:00[America/Bogota]","result":"PENDING","precondition":false,"level":0,"lineNumber":0}],"userStory":{"id":"academy-choucair","storyName":"Academy Choucair","path":"src/test/resources/features/academyChoucair.feature","narrative":"    As a user, I want to learn how to automate in screamplay at the Chourcair Academy with the automation course","type":"feature"},"featureTag":{"name":"Features/Academy Choucair","type":"feature","displayName":"Features/Academy Choucair"},"title":"Search for a automation course","tags":[{"name":"scenario1","type":"tag","displayName":"scenario1"},{"name":"Academy Choucair","type":"feature","displayName":"Academy Choucair"},{"name":"stories","type":"tag","displayName":"stories"}],"startTime":"2021-03-16T21:25:37.623722500-05:00[America/Bogota]","duration":27242,"testFailureCause":{"errorType":"net.thucydides.core.webdriver.exceptions.ElementShouldBeEnabledException","message":"Expected enabled element was not enabled","stackTrace":[{"classLoaderName":"app","declaringClass":"co.com.choucair.certification.proyectobase1.tasks.Search","methodName":"performAs","fileName":"Search.java","lineNumber":24,"format":1},{"classLoaderName":"app","declaringClass":"co.com.choucair.certification.proyectobase1.stepdefinitions.ChoucairAcademyStepDefinitions","methodName":"heSearchForTheCourseRecursosAutomatizacionBancolombiaOnTheChoucairAcademyPlatform","fileName":"ChoucairAcademyStepDefinitions.java","lineNumber":32,"format":1},{"classLoaderName":"app","declaringClass":"cucumber.runner.Runner","methodName":"runPickle","fileName":"Runner.java","lineNumber":80,"format":1}],"rootCause":{"errorType":"org.openqa.selenium.TimeoutException","message":"Expected condition failed: waiting for By.id: coursesearchbox to be enabled (tried for 5 second(s) with 100 milliseconds interval)","stackTrace":[{"classLoaderName":"app","declaringClass":"co.com.choucair.certification.proyectobase1.tasks.Search","methodName":"performAs","fileName":"Search.java","lineNumber":24,"format":1},{"classLoaderName":"app","declaringClass":"co.com.choucair.certification.proyectobase1.stepdefinitions.ChoucairAcademyStepDefinitions","methodName":"heSearchForTheCourseRecursosAutomatizacionBancolombiaOnTheChoucairAcademyPlatform","fileName":"ChoucairAcademyStepDefinitions.java","lineNumber":32,"format":1},{"classLoaderName":"app","declaringClass":"cucumber.runner.Runner","methodName":"runPickle","fileName":"Runner.java","lineNumber":80,"format":1}],"rootCause":{"errorType":"org.openqa.selenium.NoSuchElementException","message":"no such element: Unable to locate element: {\"method\":\"css selector\",\"selector\":\"#coursesearchbox\"}\n  (Session info: chrome\u003d89.0.4389.90)\nFor documentation on this error, please visit: https://www.seleniumhq.org/exceptions/no_such_element.html\nBuild info: version: \u00273.141.59\u0027, revision: \u0027e82be7d358\u0027, time: \u00272018-11-14T08:17:03\u0027\nSystem info: host: \u0027DESKTOP-NKG37V4\u0027, ip: \u0027192.168.1.7\u0027, os.name: \u0027Windows 10\u0027, os.arch: \u0027amd64\u0027, os.version: \u002710.0\u0027, java.version: \u002711.0.4\u0027\nDriver info: org.openqa.selenium.chrome.ChromeDriver\nCapabilities {acceptInsecureCerts: false, browserName: chrome, browserVersion: 89.0.4389.90, chrome: {chromedriverVersion: 89.0.4389.23 (61b08ee2c5002..., userDataDir: C:\\Users\\ramze\\AppData\\Loca...}, goog:chromeOptions: {debuggerAddress: localhost:49790}, javascriptEnabled: true, networkConnectionEnabled: false, pageLoadStrategy: normal, platform: WINDOWS, platformName: WINDOWS, proxy: Proxy(), setWindowRect: true, strictFileInteractability: false, timeouts: {implicit: 0, pageLoad: 300000, script: 30000}, unhandledPromptBehavior: dismiss and notify, webauthn:extension:largeBlob: true, webauthn:virtualAuthenticators: true}\nSession ID: 78c3fdeff0595efeedae98873b18b425\n*** Element info: {Using\u003did, value\u003dcoursesearchbox}","stackTrace":[{"classLoaderName":"app","declaringClass":"co.com.choucair.certification.proyectobase1.tasks.Search","methodName":"performAs","fileName":"Search.java","lineNumber":24,"format":1},{"classLoaderName":"app","declaringClass":"co.com.choucair.certification.proyectobase1.stepdefinitions.ChoucairAcademyStepDefinitions","methodName":"heSearchForTheCourseRecursosAutomatizacionBancolombiaOnTheChoucairAcademyPlatform","fileName":"ChoucairAcademyStepDefinitions.java","lineNumber":32,"format":1},{"classLoaderName":"app","declaringClass":"cucumber.runner.Runner","methodName":"runPickle","fileName":"Runner.java","lineNumber":80,"format":1}]}}},"testFailureClassname":"net.thucydides.core.webdriver.exceptions.ElementShouldBeEnabledException","testFailureMessage":"Expected enabled element was not enabled","testFailureSummary":"FAILURE;net.thucydides.core.webdriver.exceptions.ElementShouldBeEnabledException;Expected enabled element was not enabled;Search.java","projectKey":"","annotatedResult":"FAILURE","sessionId":"78c3fdeff0595efeedae98873b18b425","driver":"chrome:camilo","isManualTestingUpToDate":false,"manual":false,"testSource":"Cucumber","actors":[{"name":"Camilo","can":["browse the web"]}],"result":"FAILURE"}